domain_name_label_indexes/__init__.py
domain_name_label_indexes-0.1.1.dist-info/LICENSE
domain_name_label_indexes-0.1.1.dist-info/METADATA
domain_name_label_indexes-0.1.1.dist-info/WHEEL
domain_name_label_indexes-0.1.1.dist-info/top_level.txt
domain_name_label_indexes-0.1.1.dist-info/RECORD
