Metadata-Version: 2.1
Name: domain-name-label-indexes
Version: 0.1.1
Summary: Computing a domain name by it's index
Home-page: https://github.com/ralexander-phi/domain_name_label_indexes
Author: Robert Alexander
Author-email: raalexander.phi@gmail.com
License: MIT license
Keywords: domain_name_label_indexes
Platform: UNKNOWN
Classifier: Development Status :: 2 - Pre-Alpha
Classifier: Intended Audience :: Developers
Classifier: License :: OSI Approved :: MIT License
Classifier: Natural Language :: English
Classifier: Programming Language :: Python :: 3
Classifier: Programming Language :: Python :: 3.6
Classifier: Programming Language :: Python :: 3.7
Classifier: Programming Language :: Python :: 3.8
Requires-Python: >=3.6
